neurons/__init__.py
neurons_me-0.1.3.dist-info/METADATA
neurons_me-0.1.3.dist-info/WHEEL
neurons_me-0.1.3.dist-info/top_level.txt
neurons_me-0.1.3.dist-info/RECORD
