Metadata-Version: 2.4
Name: neurons.me
Version: 0.1.3
Summary: Python package for neurons.me — enabling deep learning processes and modular neural computation.
Home-page: https://github.com/neurons-me/neurons.me
Author: suiGn
Classifier: Programming Language :: Python :: 3
Requires-Python: >=3.6
Dynamic: author
Dynamic: classifier
Dynamic: description
Dynamic: description-content-type
Dynamic: home-page
Dynamic: requires-python
Dynamic: summary
